rbac/__init__.py
rbac/acl.py
rbac/context.py
rbac/proxy.py
SimpleAccessControl-0.1.1.dist-info/LICENSE
SimpleAccessControl-0.1.1.dist-info/METADATA
SimpleAccessControl-0.1.1.dist-info/WHEEL
SimpleAccessControl-0.1.1.dist-info/top_level.txt
SimpleAccessControl-0.1.1.dist-info/RECORD
