Metadata-Version: 2.1
Name: SimpleAccessControl
Version: 0.1.1
Summary: A simple role based access control utility - forked from simple-rbac by tonyseek on GitHub
Home-page: https://github.com/vyrzdev/simple-rbac
Author: Benjamin Parsons-Willis
Author-email: ben@vyrz.dev
License: MIT License
Keywords: rbac permission acl access-control permissions-system
Platform: Any
Classifier: Programming Language :: Python
Classifier: Programming Language :: Python :: 2
Classifier: Programming Language :: Python :: 3
Classifier: License :: OSI Approved :: MIT License
Classifier: Operating System :: OS Independent
Classifier: Development Status :: 4 - Beta
Classifier: Intended Audience :: Developers
Classifier: Topic :: Security
Classifier: Topic :: Software Development :: Libraries :: Python Modules
